dinbrief.py
letter.md
template.tex
dinbrief.py-0.2.0.dist-info/WHEEL
dinbrief.py-0.2.0.dist-info/METADATA
dinbrief.py-0.2.0.dist-info/RECORD
